{
  "data": {
    "result": {
      "active": 1,
      "address": "KP. Pamagersari",
      "approve": 0,
      "birthday": "1942-05-19",
      "city": "39",
      "complete_data": 1,
      "created_at": "2022-05-23 04:55:41",
      "education": "Doktor",
      "ethnic": "Dayak",
      "farmer_no": "F00009179",
      "farmer_profile": "Uploads/fphoto_3204352408920001.jpg",
      "gender": "male",
      "group_no": "-",
      "id": 9603,
      "is_dell": 0,
      "join_date": "2021-05-23",
      "kab_code": "32.04",
      "kabupaten_no": "39",
      "kecamatan": "32.04.25",
      "kode_desa": "32.04.25.99",
      "kode_kecamatan": "32.04.25",
      "kode_ta": "000001",
      "ktp_document": "Uploads/fktp_3204352408920001.jpg",
      "ktp_no": "3204352408920001",
      "main_income": "666999",
      "main_job": "Mekanik",
      "marrital_status": "Duda",
      "mou_no": "23052021_2025_2024_2023_2022_3204352408920001",
      "mu_no": "000",
      "namaDesa": "DESA-01",
      "namaKabupaten": "BANDUNG",
      "namaKecamatan": "CICALENGKA",
      "namaKelompok": "-",
      "namaMu": "TESTING",
      "namaProvinsi": "Jawa Barat",
      "namaTa": "TA_TESTING_01",
      "name": "Asep McDonald",
      "nickname": "Koko",
      "non_formal_education": "Pesantren",
      "number_family_member": 9,
      "origin": "lokal",
      "phone": "0811234567",
      "post_code": "99998",
      "province": "JB",
      "province_code": "JB",
      "religion": "konghuchu",
      "rt": 6,
      "rw": 9,
      "side_income": "999666",
      "side_job": "TNI",
      "signature": "Uploads/fttd_3204352408920001.png",
      "target_area": "000001",
      "updated_at": "2025-09-10 16:27:05",
      "user_id": "FF00001602",
      "village": "32.04.25.99"
    },
    "status": {
      "code": 200,
      "description": "success"
    }
  },
  "success": true
}
